MANIFEST.in
README.rst
setup.py
docs/HISTORY.txt
docs/LICENSE.GPL
docs/LICENSE.txt
docs/screenshot.png
ftw/__init__.py
ftw.footer.egg-info/PKG-INFO
ftw.footer.egg-info/SOURCES.txt
ftw.footer.egg-info/dependency_links.txt
ftw.footer.egg-info/entry_points.txt
ftw.footer.egg-info/namespace_packages.txt
ftw.footer.egg-info/not-zip-safe
ftw.footer.egg-info/requires.txt
ftw.footer.egg-info/top_level.txt
ftw/footer/__init__.py
ftw/footer/column.pt
ftw/footer/column.py
ftw/footer/configure.zcml
ftw/footer/footer_viewlet.pt
ftw/footer/footer_viewlet.py
ftw/footer/interfaces.py
ftw/footer/lawgiver.zcml
ftw/footer/manage-footer.pt
ftw/footer/manage.py
ftw/footer/permissions.zcml
ftw/footer/resources.zcml
ftw/footer/testing.py
ftw/footer/browser/resources/scss/footer.scss
ftw/footer/locales/ftw.footer.pot
ftw/footer/locales/ftw.lawgiver.pot
ftw/footer/locales/de/LC_MESSAGES/ftw.footer.po
ftw/footer/locales/de/LC_MESSAGES/ftw.lawgiver.po
ftw/footer/profiles/default/browserlayer.xml
ftw/footer/profiles/default/metadata.xml
ftw/footer/profiles/default/portlets.xml
ftw/footer/profiles/default/registry.xml
ftw/footer/profiles/default/rolemap.xml
ftw/footer/tests/__init__.py
ftw/footer/tests/test_footer.py
ftw/footer/tests/test_footer_functional.py