Metadata-Version: 2.1
Name: ftw.footer
Version: 1.2.1
Summary: Adds portlet columns as footer to Plone.
Home-page: https://github.com/4teamwork/ftw.footer
Author: 4teamwork AG
Author-email: mailto:info@4teamwork.ch
Maintainer: Mathias Leimgruber
License: GPL2
Keywords: plone ftw viewlet footer
Platform: UNKNOWN
Classifier: Framework :: Plone
Classifier: Framework :: Plone :: 4.3
Classifier: Framework :: Plone :: 5.1
Classifier: Programming Language :: Python
Classifier: Topic :: Software Development :: Libraries :: Python Modules
Provides-Extra: tests
